{"cameraMode":{"drawMode":0,"name":"Shaded","section":"Shading Mode"},"sceneLighting":true,"audioPlay":false,"sceneViewState":{"m_AlwaysRefresh":false,"showFog":true,"showSkybox":true,"showFlares":true,"showImageEffects":true,"showParticleSystems":true,"showVisualEffectGraphs":true,"m_FxEnabled":true},"in2DMode":false,"pivot":{"x":-1.6841583251953126,"y":3.0457499027252199,"z":2.450000762939453},"rotation":{"x":-0.08919337391853333,"y":0.5893648266792297,"z":-0.06568913161754608,"w":-0.8002379536628723},"size":7.896892070770264,"orthographic":false}